django_auto_actions/__init__.py
django_auto_actions/main.py
django_auto_actions/tests/__init__.py
django_auto_actions/tests/test_main.py
django_auto_actions-1.0.0.dist-info/LICENSE.txt
django_auto_actions-1.0.0.dist-info/METADATA
django_auto_actions-1.0.0.dist-info/WHEEL
django_auto_actions-1.0.0.dist-info/top_level.txt
django_auto_actions-1.0.0.dist-info/RECORD
