Metadata-Version: 2.1
Name: django-auto-actions
Version: 1.0.0
Summary: Automatically generates Django admin actions based on your model's fields
Home-page: https://github.com/Flexonze/django-auto-actions
Author: Félix Gravel
Author-email: felix.gravel@tlmgo.com
License: MIT
Classifier: License :: OSI Approved :: MIT License
Classifier: Intended Audience :: Developers
Classifier: Operating System :: OS Independent
Classifier: Programming Language :: Python
Classifier: Programming Language :: Python :: 3.9
Classifier: Programming Language :: Python :: 3.10
Classifier: Programming Language :: Python :: 3.11
Classifier: Programming Language :: Python :: 3.12
Classifier: Topic :: Software Development :: Libraries :: Python Modules
Classifier: Framework :: Django
Classifier: Framework :: Django :: 4.2
Classifier: Framework :: Django :: 5.1
Requires-Python: >=3.9
License-File: LICENSE.txt
Requires-Dist: Django>=4.2
